chronica/__init__.py
chronica/rpc/__init__.py
chronica/rpc/communicator_pb2.py
chronica/rpc/communicator_pb2.pyi
chronica/rpc/communicator_pb2_grpc.py
chronica/sys/__init__.py
chronica/sys/sysmodule.py
chronica/torch/__init__.py
chronica/torch/utils/__init__.py
chronica/torch/utils/data/__init__.py
chronica/torch/utils/data/dataset.py
chronica/torch/utils/data/distributed.py
chronica-0.2.6.dist-info/LICENSE
chronica-0.2.6.dist-info/METADATA
chronica-0.2.6.dist-info/WHEEL
chronica-0.2.6.dist-info/top_level.txt
chronica-0.2.6.dist-info/RECORD
