Metadata-Version: 2.1
Name: chronica
Version: 0.2.6
Summary: A data-imbalance-aware scheduler for distributed deep learning
Author: Sogang University
License: From Google's B-tree implementation for Go:
Project-URL: homepage, https://github.com/9rum/chronica
Keywords: distributed deep learning,straggler,scheduler,data imbalance
Classifier: Programming Language :: Python :: 3.6
Classifier: Programming Language :: Python :: 3.7
Classifier: Programming Language :: Python :: 3.8
Classifier: Programming Language :: Python :: 3.9
Classifier: Programming Language :: Python :: 3.10
Classifier: Programming Language :: Python :: 3.11
Classifier: Programming Language :: Python :: 3.12
Classifier: License :: OSI Approved :: Apache Software License
Classifier: Operating System :: OS Independent
Requires-Python: >=3.6
License-File: LICENSE
Requires-Dist: grpcio
Requires-Dist: numpy
Requires-Dist: protobuf
Requires-Dist: scikit-learn
Requires-Dist: torch
